numpy_aarange/__init__.py
numpy_aarange/__main__.py
numpy_aarange/aarange.py
numpy_aarange_yagodanr-0.1.1.dist-info/METADATA
numpy_aarange_yagodanr-0.1.1.dist-info/WHEEL
numpy_aarange_yagodanr-0.1.1.dist-info/entry_points.txt
numpy_aarange_yagodanr-0.1.1.dist-info/top_level.txt
numpy_aarange_yagodanr-0.1.1.dist-info/RECORD
