Metadata-Version: 2.4
Name: numpy_aarange_yagodanr
Version: 0.1.1
Summary: A simple implementation of numpy.arange
Requires-Python: >=3.9
Requires-Dist: numpy
